[
  { "source_payment_terms": "14 Days", "workday_payment_terms": "NET 14" },
  { "source_payment_terms": "15 Days", "workday_payment_terms": "NET 21" },
  { "source_payment_terms": "21 Days", "workday_payment_terms": "NET 21" },
  { "source_payment_terms": "30 Days", "workday_payment_terms": "Net 30" },
  { "source_payment_terms": "30 EOM", "workday_payment_terms": "EOM + 30 D" },
  { "source_payment_terms": "30 days", "workday_payment_terms": "Net 30" },
  { "source_payment_terms": "7 Days", "workday_payment_terms": "Net 7" },
  { "source_payment_terms": "Due Immediately", "workday_payment_terms": "Immediate" },
  { "source_payment_terms": "60 Days", "workday_payment_terms": "Net 60" },
  { "source_payment_terms": "90 Days", "workday_payment_terms": "Net 90" },
  { "source_payment_terms": "120 Days", "workday_payment_terms": "Net 120" }
]